dfpy/.DS_Store
dfpy/__init__.py
dfpy/dfpy.py
BRDFP-0.0.1.dist-info/WHEEL
BRDFP-0.0.1.dist-info/METADATA
BRDFP-0.0.1.dist-info/licenses/LICENSE
BRDFP-0.0.1.dist-info/RECORD
