Metadata-Version: 2.1
Name: BRDFP
Version: 0.0.1
Summary: Demonstrativos Financeiros CVM
Author-email: Andre Amorim <andre.a.silveira@icloud.com>
Requires-Python: >=3.7
